setup.py
LiMaoreng/ChangYong.py
LiMaoreng/JiaoBen.py
LiMaoreng/YouJian.py
LiMaoreng/__init__.py
LiMaoreng/ceshi.py
LiMaoreng.egg-info/PKG-INFO
LiMaoreng.egg-info/SOURCES.txt
LiMaoreng.egg-info/dependency_links.txt
LiMaoreng.egg-info/top_level.txt