Metadata-Version: 2.1
Name: LiMaoreng
Version: 0.0.7
Summary: 李茂仍的常用Python小功能。     0.0.1版为测试版，无具体功能。     0.0.2版提供了李茂仍常用的简单脚本功能。     0.0.3版修复了部分错误。     0.0.4版移除了“锁定”函数的递归，改为循环。     0.0.7版移除了自动下载第三方库功能。
Home-page: https://github.com/
Author: 李茂仍
Author-email: 2324412934@qq.com
License: UNKNOWN
Platform: UNKNOWN
Classifier: Programming Language :: Python :: 3
Classifier: License :: OSI Approved :: MIT License 
Classifier: Operating System :: OS Independent
